{
  "html": "<tr><td><a title=\"Link to attachment for 2025-0610\" href=\"attachment.php?attach=47507&amp;lang=en\">2025-0610</a><br></td><td>2025-08-11</td><td class=\"\"></td><td class=\"\"></td><td class=\"\"></td><td>JUS</td><td>Other Than Statutory Authority</td><td>Appointment to the Superior Court of Justice of Ontario</td><td>Appointment of Jennifer M. Moser of the city of London, in the Province of Ontario, Barrister-at-law, to be a Judge of the Superior Court of Justice of Ontario, and a Judge ex officio of the Court of Appeal for Ontario.</td><td aria-label=\"not applicable\">N/A</td></tr>",
  "pcNumber": "2025-0610",
  "date": "2025-08-11",
  "chapter": "",
  "chapterYear": "",
  "bill": "",
  "department": "JUS",
  "act": "Other Than Statutory Authority",
  "subject": "Appointment to the Superior Court of Justice of Ontario",
  "precis": "Appointment of Jennifer M. Moser of the city of London, in the Province of Ontario, Barrister-at-law, to be a Judge of the Superior Court of Justice of Ontario, and a Judge ex officio of the Court of Appeal for Ontario.",
  "registration": "N/A",
  "attachments": [
    "47507"
  ],
  "htmlHash": "115e675d81220d9ca3afef7f746a5e81"
}