{
  "html": "<tr><td><a title=\"Link to attachment for 2025-0883\" href=\"attachment.php?attach=47829&amp;lang=en\">2025-0883</a><br></td><td>2025-12-04</td><td class=\"\"></td><td class=\"\"></td><td class=\"\"></td><td>GAC</td><td>State Immunity Act</td><td>Order amending the Order Establishing a List of Foreign State Supporters of Terrorism</td><td>Order amending the Order Establishing a List of Foreign State Supporters of Terrorism in order to remove the Syrian Arab Republic from the schedule of the Order.\n\t\t</td><td aria-label=\"not applicable\">N/A</td></tr>",
  "pcNumber": "2025-0883",
  "date": "2025-12-04",
  "chapter": "",
  "chapterYear": "",
  "bill": "",
  "department": "GAC",
  "act": "State Immunity Act",
  "subject": "Order amending the Order Establishing a List of Foreign State Supporters of Terrorism",
  "precis": "Order amending the Order Establishing a List of Foreign State Supporters of Terrorism in order to remove the Syrian Arab Republic from the schedule of the Order.",
  "registration": "N/A",
  "attachments": [
    "47829"
  ],
  "htmlHash": "82ce0a587887c7c1486a617ab65d8d7e"
}