{
  "html": "<tr><td><a title=\"Link to attachment for 2025-0621\" href=\"attachment.php?attach=47522&amp;lang=en\">2025-0621</a><br></td><td>2025-08-26</td><td class=\"\"></td><td class=\"\"></td><td class=\"\"></td><td>PMO</td><td>National Security and Intelligence Committee of Parliamentarians Act</td><td>Appointment of a member of the National Security and Intelligence Committee of Parliamentarians</td><td>Appointment of Abdelhaq Sari, a member of the House of Commons who belongs to the government party, to be a member of the National Security and Intelligence Committee of Parliamentarians.</td><td aria-label=\"not applicable\">N/A</td></tr>",
  "pcNumber": "2025-0621",
  "date": "2025-08-26",
  "chapter": "",
  "chapterYear": "",
  "bill": "",
  "department": "PMO",
  "act": "National Security and Intelligence Committee of Parliamentarians Act",
  "subject": "Appointment of a member of the National Security and Intelligence Committee of Parliamentarians",
  "precis": "Appointment of Abdelhaq Sari, a member of the House of Commons who belongs to the government party, to be a member of the National Security and Intelligence Committee of Parliamentarians.",
  "registration": "N/A",
  "attachments": [
    "47522"
  ],
  "htmlHash": "9af2bca17f80031f4dc0a78c024e4b2f"
}