{
  "html": "<tr><td><a title=\"Link to attachment for 2025-0544\" href=\"attachment.php?attach=47416&amp;lang=en\">2025-0544</a><br></td><td>2025-06-27</td><td class=\"\"></td><td class=\"\"></td><td class=\"\"></td><td>FA</td><td>Other Than Statutory Authority</td><td>Appointment of the Consul General of Canada in Istanbul (Republic of T端rkiye)</td><td>Appointment of Natalie Britton as Consul General of Canada in Istanbul (Republic of T端rkiye).</td><td aria-label=\"not applicable\">N/A</td></tr>",
  "pcNumber": "2025-0544",
  "date": "2025-06-27",
  "chapter": "",
  "chapterYear": "",
  "bill": "",
  "department": "FA",
  "act": "Other Than Statutory Authority",
  "subject": "Appointment of the Consul General of Canada in Istanbul (Republic of T端rkiye)",
  "precis": "Appointment of Natalie Britton as Consul General of Canada in Istanbul (Republic of T端rkiye).",
  "registration": "N/A",
  "attachments": [
    "47416"
  ],
  "htmlHash": "53d1c631c68febf430f88ec361198578"
}