{
  "html": "<tr><td><a title=\"Link to attachment for 2025-0857\" href=\"attachment.php?attach=47800&amp;lang=en\">2025-0857</a><br></td><td>2025-11-28</td><td class=\"\"></td><td class=\"\"></td><td class=\"\"></td><td>FIN</td><td>Canadian International Trade Tribunal Act</td><td>Regulations Amending the Canadian International Trade Tribunal Procurement Inquiry Regulations\n</td><td>Regulations Amending the Canadian International Trade Tribunal Procurement Inquiry Regulations in order to (1) amend the Regulations to specify aspects of a procurement process that the Canadian International Trade Tribunal is not authorized to inquire into, namely aspects of a procurement process that relates to Canadian suppliers and content or limiting procurements to small businesses; and (2) includes a transitional provision specifying the date after which these amendments would apply to complaints that are filed.</td><td><strong>Registration: </strong>SOR/2025-0247  <strong>Publication Date:</strong> 2025-12-17</td></tr>",
  "pcNumber": "2025-0857",
  "date": "2025-11-28",
  "chapter": "",
  "chapterYear": "",
  "bill": "",
  "department": "FIN",
  "act": "Canadian International Trade Tribunal Act",
  "subject": "Regulations Amending the Canadian International Trade Tribunal Procurement Inquiry Regulations",
  "precis": "Regulations Amending the Canadian International Trade Tribunal Procurement Inquiry Regulations in order to (1) amend the Regulations to specify aspects of a procurement process that the Canadian International Trade Tribunal is not authorized to inquire into, namely aspects of a procurement process that relates to Canadian suppliers and content or limiting procurements to small businesses; and (2) includes a transitional provision specifying the date after which these amendments would apply to complaints that are filed.",
  "registration": "Registration: SOR/2025-0247 Publication Date: 2025-12-17",
  "attachments": [
    "47800"
  ],
  "htmlHash": "eb0f0ae2aad637915fed1e12ae3d4a16"
}