{
  "html": "<tr><td><a title=\"Link to attachment for 2025-0689\" href=\"attachment.php?attach=47608&amp;lang=en\">2025-0689</a><br></td><td>2025-09-25</td><td class=\"\"></td><td class=\"\"></td><td class=\"\"></td><td>IRCC</td><td>Immigration and Refugee Protection Act</td><td>Reappointment of a full-time member of the Immigration and Refugee Board (Montréal Regional Office)</td><td>Reappointment of Roch Côté of Ottawa, Ontario, as a full-time member of the Immigration and Refugee Board (Ottawa District Office), to hold office during good behaviour for a term of five years, effective October 6, 2025.</td><td aria-label=\"not applicable\">N/A</td></tr>",
  "pcNumber": "2025-0689",
  "date": "2025-09-25",
  "chapter": "",
  "chapterYear": "",
  "bill": "",
  "department": "IRCC",
  "act": "Immigration and Refugee Protection Act",
  "subject": "Reappointment of a full-time member of the Immigration and Refugee Board (Montréal Regional Office)",
  "precis": "Reappointment of Roch Côté of Ottawa, Ontario, as a full-time member of the Immigration and Refugee Board (Ottawa District Office), to hold office during good behaviour for a term of five years, effective October 6, 2025.",
  "registration": "N/A",
  "attachments": [
    "47608"
  ],
  "htmlHash": "c3a2d5f5aaafaa8e58a79c8883adc5f3"
}