{
  "html": "<tr><td><a title=\"Link to attachment for 2026-0091\" href=\"attachment.php?attach=48067&amp;lang=en\">2026-0091</a><br></td><td>2026-02-03</td><td class=\"\"></td><td class=\"\"></td><td class=\"\"></td><td>AAFC</td><td>Farm Credit Canada Act</td><td>Reappointment of a director of the Board of Directors of Farm Credit Canada</td><td>Approval of the reappointment by the Minister of Agriculture and Agri-Food of Michael Tees of North Vancouver, British Columbia, as a director of the Board of Directors of Farm Credit Canada, to hold office during pleasure for a term of three years.</td><td aria-label=\"not applicable\">N/A</td></tr>",
  "pcNumber": "2026-0091",
  "date": "2026-02-03",
  "chapter": "",
  "chapterYear": "",
  "bill": "",
  "department": "AAFC",
  "act": "Farm Credit Canada Act",
  "subject": "Reappointment of a director of the Board of Directors of Farm Credit Canada",
  "precis": "Approval of the reappointment by the Minister of Agriculture and Agri-Food of Michael Tees of North Vancouver, British Columbia, as a director of the Board of Directors of Farm Credit Canada, to hold office during pleasure for a term of three years.",
  "registration": "N/A",
  "attachments": [
    "48067"
  ],
  "htmlHash": "8c9bfd8b1b89cf1f04869fe2c5f724f2"
}