{
  "html": "<tr><td><a title=\"Link to attachment for 2026-0475\" href=\"attachment.php?attach=48590&amp;lang=en\">2026-0475</a><br></td><td>2026-05-26</td><td class=\"\"></td><td class=\"\"></td><td class=\"\"></td><td>ESDC</td><td>Department of Employment and Social Development Act</td><td>Appointment of a member of the Employment Insurance Board of Appeal</td><td>Appointment of Kari Jane Schroeder of Calgary, Alberta, to be a member of the Employment Insurance Board of Appeal, to hold office during pleasure on a part-time basis for a term of five years.</td><td aria-label=\"not applicable\">N/A</td></tr>",
  "pcNumber": "2026-0475",
  "date": "2026-05-26",
  "chapter": "",
  "chapterYear": "",
  "bill": "",
  "department": "ESDC",
  "act": "Department of Employment and Social Development Act",
  "subject": "Appointment of a member of the Employment Insurance Board of Appeal",
  "precis": "Appointment of Kari Jane Schroeder of Calgary, Alberta, to be a member of the Employment Insurance Board of Appeal, to hold office during pleasure on a part-time basis for a term of five years.",
  "registration": "N/A",
  "attachments": [
    "48590"
  ],
  "htmlHash": "6a8975a22a736e12f6b70f14a1a7ed50"
}