{
  "html": "<tr><td><a title=\"Link to attachment for 2026-0437\" href=\"attachment.php?attach=48549&amp;lang=en\">2026-0437</a><br></td><td>2026-05-08</td><td class=\"\"></td><td class=\"\"></td><td class=\"\"></td><td>NA, CIRNAC</td><td>Yukon Act</td><td>Relinquishement of the administration and control from the Commissioner of Yukon\n</td><td>Order approving the relinquishment in perpetuity, by the Commissioner of Yukon, of the administration and control of the public real properties located in the community of Ross River, Yukon, and transfer of the administration of those properties to the Minister of Northern Affairs.</td><td aria-label=\"not applicable\">N/A</td></tr>",
  "pcNumber": "2026-0437",
  "date": "2026-05-08",
  "chapter": "",
  "chapterYear": "",
  "bill": "",
  "department": "NA, CIRNAC",
  "act": "Yukon Act",
  "subject": "Relinquishement of the administration and control from the Commissioner of Yukon",
  "precis": "Order approving the relinquishment in perpetuity, by the Commissioner of Yukon, of the administration and control of the public real properties located in the community of Ross River, Yukon, and transfer of the administration of those properties to the Minister of Northern Affairs.",
  "registration": "N/A",
  "attachments": [
    "48549"
  ],
  "htmlHash": "3e83817a7d9b8c5a457face402aa6415"
}