{
  "html": "<tr><td><a title=\"Link to attachment for 2026-0492\" href=\"attachment.php?attach=48607&amp;lang=en\">2026-0492</a><br></td><td>2026-05-26</td><td class=\"\"></td><td class=\"\"></td><td class=\"\"></td><td>TC</td><td>Federal Public Sector Labour Relations and Employment Board Act</td><td>Reappointment of a full-time member of the Federal Public Sector Labour Relations and Employment Board</td><td>Reappointment of Caroline Engmann of Ottawa, Ontario, as a full-time member of the Federal Public Sector Labour Relations and Employment Board, to hold office during good behaviour for a term of five years, effective September 13, 2026.</td><td aria-label=\"not applicable\">N/A</td></tr>",
  "pcNumber": "2026-0492",
  "date": "2026-05-26",
  "chapter": "",
  "chapterYear": "",
  "bill": "",
  "department": "TC",
  "act": "Federal Public Sector Labour Relations and Employment Board Act",
  "subject": "Reappointment of a full-time member of the Federal Public Sector Labour Relations and Employment Board",
  "precis": "Reappointment of Caroline Engmann of Ottawa, Ontario, as a full-time member of the Federal Public Sector Labour Relations and Employment Board, to hold office during good behaviour for a term of five years, effective September 13, 2026.",
  "registration": "N/A",
  "attachments": [
    "48607"
  ],
  "htmlHash": "be233c85ddd54fd6c6f4855b4751be1f"
}