{
  "html": "<tr><td><a title=\"Link to attachment for 2026-0444\" href=\"attachment.php?attach=48556&amp;lang=en\">2026-0444</a><br></td><td>2026-05-13</td><td class=\"\"></td><td class=\"\"></td><td class=\"\"></td><td>PMO</td><td>Public Service Employment Act</td><td>Appointment of a member of the Independent Advisory Board for Supreme Court of Canada Judicial Appointments</td><td>Appointment of Justin Edward Kingston of Edmonton, Alberta, to be a special adviser to the Prime Minister, to serve as a member of the Independent Advisory Board for Supreme Court of Canada Judicial Appointments, to hold office during pleasure for a term of one year.</td><td aria-label=\"not applicable\">N/A</td></tr>",
  "pcNumber": "2026-0444",
  "date": "2026-05-13",
  "chapter": "",
  "chapterYear": "",
  "bill": "",
  "department": "PMO",
  "act": "Public Service Employment Act",
  "subject": "Appointment of a member of the Independent Advisory Board for Supreme Court of Canada Judicial Appointments",
  "precis": "Appointment of Justin Edward Kingston of Edmonton, Alberta, to be a special adviser to the Prime Minister, to serve as a member of the Independent Advisory Board for Supreme Court of Canada Judicial Appointments, to hold office during pleasure for a term of one year.",
  "registration": "N/A",
  "attachments": [
    "48556"
  ],
  "htmlHash": "c84a759ba6b96ab32067e3a1c428fff9"
}