{
  "html": "<tr><td><a title=\"Link to attachment for 2026-0245\" href=\"attachment.php?attach=48329&amp;lang=en\">2026-0245</a><br></td><td>2026-03-24</td><td class=\"\"></td><td class=\"\"></td><td class=\"\"></td><td>ESDC</td><td>Accessible Canada Act</td><td>Reappointment of a director of the Canadian Accessibility Standards Development Organization</td><td>Reappointment of William Kirkwood Adair of Toronto, Ontario, as a director of the Canadian Accessibility Standards Development Organization, to hold office during pleasure for a term of three years, effective March 25, 2026.</td><td aria-label=\"not applicable\">N/A</td></tr>",
  "pcNumber": "2026-0245",
  "date": "2026-03-24",
  "chapter": "",
  "chapterYear": "",
  "bill": "",
  "department": "ESDC",
  "act": "Accessible Canada Act",
  "subject": "Reappointment of a director of the Canadian Accessibility Standards Development Organization",
  "precis": "Reappointment of William Kirkwood Adair of Toronto, Ontario, as a director of the Canadian Accessibility Standards Development Organization, to hold office during pleasure for a term of three years, effective March 25, 2026.",
  "registration": "N/A",
  "attachments": [
    "48329"
  ],
  "htmlHash": "1a3c651412383afe18a73995461645ae"
}